.gitignore
.travis.yml
CHANGES.rst
LICENSE
MANIFEST.in
README.rst
argon2pure.py
setup.cfg
setup.py
test_argon2pure.py
argon2pure.egg-info/PKG-INFO
argon2pure.egg-info/SOURCES.txt
argon2pure.egg-info/dependency_links.txt
argon2pure.egg-info/pbr.json
argon2pure.egg-info/requires.txt
argon2pure.egg-info/top_level.txt
argon2pure.egg-info/zip-safe