Metadata-Version: 1.1
Name: argon2pure
Version: 1.1.1
Summary: Pure python implementation of the ARGON2 password hash
Home-page: http://github.com/bwesterb/argon2pure
Author: Bas Westerbaan
Author-email: bas@westerbaan.name
License: MIT
Platform: UNKNOWN
Classifier: Development Status :: 4 - Beta
Classifier: License :: OSI Approved :: MIT License
Classifier: Operating System :: POSIX
Classifier: Topic :: Security
Classifier: Programming Language :: Python :: 2.6
Classifier: Programming Language :: Python :: 2.7
Classifier: Programming Language :: Python :: 3.2
Classifier: Programming Language :: Python :: 3.3
Classifier: Programming Language :: Python :: 3.4
Classifier: Programming Language :: Python :: 3.5
